Workbook

Sheet Monthly Financials
A1: Month | B1: Revenue | C1: Expenses | D1: Net Profit | E1: Profit Margin | F1: Projects Active | G1: New Commissions | H1: Staff Count | I1: Utilization Rate
A2: 45658 | B2: 425000 | C2: 375000 | D2: =B2-C2 -> 50000 | E2: =D2/B2 -> 0.11764706 | F2: 9 | G2: 2 | H2: 24 | I2: 0.72
A3: 45689 | B3: 440000 | C3: 380000 | D3: =B3-C3 -> 60000 | E3: =D3/B3 -> 0.13636364 | F3: 10 | G3: 1 | H3: 24 | I3: 0.74
A4: 45717 | B4: 485000 | C4: 395000 | D4: =B4-C4 -> 90000 | E4: =D4/B4 -> 0.18556701 | F4: 11 | G4: 3 | H4: 25 | I4: 0.78
A5: 45748 | B5: 520000 | C5: 410000 | D5: =B5-C5 -> 110000 | E5: =D5/B5 -> 0.21153846 | F5: 12 | G5: 2 | H5: 25 | I5: 0.8
A6: 45778 | B6: 545000 | C6: 425000 | D6: =B6-C6 -> 120000 | E6: =D6/B6 -> 0.22018349 | F6: 13 | G6: 2 | H6: 26 | I6: 0.82
A7: 45809 | B7: 490000 | C7: 415000 | D7: =B7-C7 -> 75000 | E7: =D7/B7 -> 0.15306122 | F7: 12 | G7: 1 | H7: 26 | I7: 0.75
A8: 45839 | B8: 430000 | C8: 390000 | D8: =B8-C8 -> 40000 | E8: =D8/B8 -> 0.093023256 | F8: 10 | G8: 0 | H8: 25 | I8: 0.68
A9: 45870 | B9: 415000 | C9: 385000 | D9: =B9-C9 -> 30000 | E9: =D9/B9 -> 0.072289157 | F9: 9 | G9: 1 | H9: 25 | I9: 0.65
A10: 45901 | B10: 505000 | C10: 405000 | D10: =B10-C10 -> 100000 | E10: =D10/B10 -> 0.1980198 | F10: 11 | G10: 3 | H10: 25 | I10: 0.79
A11: 45931 | B11: 570000 | C11: 440000 | D11: =B11-C11 -> 130000 | E11: =D11/B11 -> 0.22807018 | F11: 14 | G11: 3 | H11: 26 | I11: 0.84
A12: 45962 | B12: 595000 | C12: 465000 | D12: =B12-C12 -> 130000 | E12: =D12/B12 -> 0.21848739 | F12: 15 | G12: 2 | H12: 27 | I12: 0.85
A13: 45992 | B13: 480000 | C13: 420000 | D13: =B13-C13 -> 60000 | E13: =D13/B13 -> 0.125 | F13: 12 | G13: 1 | H13: 26 | I13: 0.7
... A16: 46082 | B16: 560000 | C16: 450000 | D16: =B16-C16 -> 110000 | E16: =D16/B16 -> 0.19642857 | F16: 14 | G16: 3 | H16: 28 | I16: 0.81
A17: TOTALS | B17: =SUM(B2:B16) -> 7505000 | C17: =SUM(C2:C16) -> 6225000 | D17: =SUM(D2:D16) -> 1280000
A18: AVERAGES | B18: =AVERAGE(B2:B16) -> 500333.33 | C18: =AVERAGE(C2:C16) -> 415000 | E18: =AVERAGE(E2:E16) -> 0.16600747 | F18: =AVERAGE(F2:F16) -> 11.8 | G18: =AVERAGE(G2:G16) -> 1.8 | H18: =AVERAGE(H2:H16) -> 25.733333 | I18: =AVERAGE(I2:I16) -> 0.76466667

Sheet Staff Roster
A1: Name | B1: Department | C1: Role | D1: Location | E1: Current Project | F1: Allocation Pct | G1: Billable Hours This Month | H1: Utilization Target | I1: Utilization Gap | J1: Skills | K1: Availability Next Month | L1: Start Date | M1: Notes
A2: Eran Chen | B2: Executive | C2: Managing Principal | D2: New York | E2: Firm-wide / The Mira Hotel | F2: 0.3 | G2: 42 | H2: 0.5 | I2: =IF(G2="","",G2/(160*H2)-1) -> -0.475 | J2: Leadership; Client Relations; Design Direction | K2: Available for new project oversight | L2: 39156 | M2: Splitting time across Mira Hotel pitch and firm management
A3: Nile Lichtenstein | B3: Executive | C3: Principal | D3: New York | E3: Shore Club Residences | F3: 0.4 | G3: 56 | H3: 0.5 | I3: =IF(G3="","",G3/(160*H3)-1) -> -0.3 | J3: Leadership; Design Review; Client Relations | K3: Limited - Shore Club CD push | L3: 39965 | M3: Leading Shore Club design vision through CD phase
A4: Megumi Takata | B4: Executive | C4: Chief Operating Officer | D4: New York | E4: Operations | F4: 0.1 | G4: 14 | H4: 0.25 | I4: =IF(G4="","",G4/(160*H4)-1) -> -0.65 | J4: Operations; Finance; HR Oversight | K4: Available | L4: 40918 | M4: Operational oversight; not project-billable
A5: Akshay Mehra | B5: Architecture | C5: Project Architect | D5: New York | E5: Shore Club Residences | F5: 1 | G5: 148 | H5: 0.85 | I5: =IF(G5="","",G5/(160*H5)-1) -> 0.088235294 | J5: Revit; Bluebeam; Permit Coordination; Consultant Mgmt | K5: Unavailable - Shore Club CD deadline | L5: 42625 | M5: OVERALLOCATED: working nights to meet 50% CD issuance
A6: Yinxing Liu | B6: Architecture | C6: Design Team Lead | D6: New York | E6: Upstate Condo | F6: 0.9 | G6: 126 | H6: 0.85 | I6: =IF(G6="","",G6/(160*H6)-1) -> -0.073529412 | J6: Revit; Rhino; Team Management; Design Review | K6: Partially available after DD milestone | L6: 42114 | M6: Also training junior staff on Revit workflows
A7: Carlos Rivera | B7: Architecture | C7: Senior Designer | D7: Fort Lauderdale | E7: Shore Club Residences | F7: 0.85 | G7: 119 | H7: 0.85 | I7: =IF(G7="","",G7/(160*H7)-1) -> -0.125 | J7: Rhino; AutoCAD; SketchUp; Facade Design | K7: Limited - CD phase | L7: 43136 | M7: Supporting facade documentation for Shore Club
A8: Priya Narayanan | B8: Architecture | C8: BIM Manager | D8: New York | E8: Mayflower / Shore Club | F8: 1.1 | G8: 154 | H8: 0.85 | I8: =IF(G8="","",G8/(160*H8)-1) -> 0.13235294 | J8: Revit; BIM 360; Navisworks; Clash Detection | K8: Unavailable | L8: 43040 | M8: OVERALLOCATED: split across two CD-phase projects
A9: Sarah Kim | B9: Architecture | C9: Interior Designer | D9: New York | E9: Shore Club Residences / Riverside Tower | F9: 0.95 | G9: 133 | H9: 0.85 | I9: =IF(G9="","",G9/(160*H9)-1) -> -0.022058824 | J9: Interior Design; InDesign; Photoshop; Material Selection | K9: Limited | L9: 43696 | M9: Interiors for Shore Club units and Riverside amenity spaces
A10: David Okonkwo | B10: Architecture | C10: Project Manager | D10: Fort Lauderdale | E10: Shore Club Residences | F10: 1 | G10: 140 | H10: 0.85 | I10: =IF(G10="","",G10/(160*H10)-1) -> 0.029411765 | J10: Project Management; Scheduling; Budget Tracking | K10: Unavailable | L10: 43843 | M10: Managing Shore Club construction admin coordination
A11: Hannah Bergstrom | B11: Architecture | C11: Junior Designer | D11: New York | E11: Riverside Tower | F11: 0.8 | G11: 112 | H11: 0.85 | I11: =IF(G11="","",G11/(160*H11)-1) -> -0.17647059 | J11: Rhino; Grasshopper; SketchUp; Visualization | K11: Available 20% | L11: 45082 | M11: Supporting DD drawings for Riverside Tower
A12: Marco Vitale | B12: Architecture | C12: Facade Consultant | D12: Remote | E12: Shore Club / Mayflower | F12: 1 | G12: 140 | H12: 0.85 | I12: =IF(G12="","",G12/(160*H12)-1) -> 0.029411765 | J12: Facade Engineering; Waterproofing; Thermal Analysis | K12: Unavailable | L12: 44277 | M12: Reviewing facade details across two active CD sets
A13: Aisha Patel | B13: Architecture | C13: Sustainability Lead | D13: New York | E13: Jersey City Waterfront Tower | F13: 0.6 | G13: 84 | H13: 0.85 | I13: =IF(G13="","",G13/(160*H13)-1) -> -0.38235294 | J13: LEED; Energy Modeling; Sustainability Reporting | K13: Available 40% for new SD project | L13: 43599 | M13: Early-stage sustainability framework for Jersey City
... A20: Ryoko Okada | B20: Interior | C20: Principal Interior | D20: New York | E20: Shore Club / Hoboken Residential | F20: 1 | G20: 140 | H20: 0.8 | I20: =IF(G20="","",G20/(160*H20)-1) -> 0.09375 | J20: Bluebeam; Photoshop; InDesign; Interior Specifications | K20: Unavailable | L20: 42614 | M20: Reviewing interior markups across two projects
A21: Lily Tran | B21: Marketing | C21: Marketing Manager | D21: New York | E21: Firm-wide | I21: =IF(G21="","",G21/(160*H21)-1) | J21: InDesign; Photoshop; RFP Assembly; PR Coordination | K21: Available | L21: 44105 | M21: Award season - coordinating AIA and Architizer submissions
A22: Derek Washington | B22: Marketing | C22: Graphic Designer | D22: Remote | E22: Firm-wide | I22: =IF(G22="","",G22/(160*H22)-1) | J22: InDesign; Illustrator; Photoshop; Presentation Design | K22: Available | L22: 44389 | M22: Building RFP template system
A23: Sofia Hernandez | B23: Marketing | C23: Content Strategist | D23: New York | E23: Firm-wide | I23: =IF(G23="","",G23/(160*H23)-1) | J23: Copywriting; Social Media; Website Content | K23: Available | L23: 44669 | M23: Website refresh content development
A24: Nina Kovalenko | B24: Marketing | C24: Social Media Coordinator | D24: Remote | E24: Firm-wide | I24: =IF(G24="","",G24/(160*H24)-1) | J24: Social Media; Content Calendar; Analytics | K24: Available | L24: 44935 | M24: Managing Instagram and LinkedIn content
A25: Thalia Morrison | B25: Executive | C25: Executive Assistant | D25: New York | E25: Executive Support | I25: =IF(G25="","",G25/(160*H25)-1) | J25: Outlook; Scheduling; Travel Planning; ZoomInfo | K25: Available | L25: 43276 | M25: Supporting Eran Chen - travel season upcoming
A26: Robert Flanagan | B26: HR | C26: HR Director | D26: New York | E26: HR Operations | I26: =IF(G26="","",G26/(160*H26)-1) | J26: Recruiting; Policy; Compliance; Benefits Admin | K26: Available | L26: 42415 | M26: Overseeing onboarding for two new hires in April
A27: Jessica Chu | B27: HR | C27: Recruiting Coordinator | D27: New York | E27: HR Operations | I27: =IF(G27="","",G27/(160*H27)-1) | J27: Recruiting; Interview Scheduling; Job Postings | K27: Available | L27: 44872 | M27: Active searches: 2 junior designers + 1 project architect
A28: Sam Petrov | B28: Operations | C28: Office Manager | D28: New York | E28: Office Operations | I28: =IF(G28="","",G28/(160*H28)-1) | J28: Facilities; Vendor Management; Office Systems | K28: Available | L28: 43535 | M28: Coordinating new seating plan for April hires
A29: Diana Reyes | B29: Operations | C29: IT Administrator | D29: New York | E29: IT Infrastructure | I29: =IF(G29="","",G29/(160*H29)-1) | J29: IT Admin; Software Licensing; Server Management | K29: Available | L29: 44067 | M29: Revit license allocation and server maintenance
A30: Kevin O'Brien | B30: Operations | C30: Finance Manager | D30: New York | E30: Finance | I30: =IF(G30="","",G30/(160*H30)-1) | J30: QuickBooks; Excel; Budgeting; Invoicing; Payroll | K30: Available | L30: 42885 | M30: QuickBooks Desktop to Online migration underway
A31: Fatima Al-Rashid | B31: Operations | C31: Procurement Specialist | D31: Fort Lauderdale | E31: Shore Club Residences | I31: =IF(G31="","",G31/(160*H31)-1) | J31: Procurement; Vendor Relations; Material Sourcing | K31: Available | L31: 44487 | M31: Sourcing facade material samples for Shore Club
A32: Ben Torres | B32: Operations | C32: Facilities Coordinator | D32: New York | E32: Office Operations | I32: =IF(G32="","",G32/(160*H32)-1) | J32: Facilities; Maintenance; Space Planning | K32: Available | L32: 45019 | M32: Updating Illustrator seating chart for new hires
A33: OPEN POSITION | B33: Architecture | C33: Junior Designer | D33: New York | E33: Riverside Tower | F33: 0 | G33: 0 | H33: 0.85 | I33: =IF(G33="","",G33/(160*H33)-1) -> -1 | J33: Rhino; SketchUp; Visualization | K33: Start date: May 2026 | M33: Interviewing candidates - need for DD support
A34: OPEN POSITION | B34: Architecture | C34: Project Architect | D34: Fort Lauderdale | E34: TBD | F34: 0 | G34: 0 | H34: 0.85 | I34: =IF(G34="","",G34/(160*H34)-1) -> -1 | J34: Revit; Bluebeam; CD Experience; Permit Coordination | K34: Start date: June 2026 | M34: Need for growing Fort Lauderdale workload
A35: TBD | B35: Architecture | C35: Intern | D35: New York | E35: TBD | F35: 0 | G35: 0 | H35: 0.5 | I35: =IF(G35="","",G35/(160*H35)-1) -> -1 | J35: Rhino; AutoCAD; Adobe Suite | K35: Start date: Summer 2026 | M35: Summer intern position
A36: TBD | B36: Marketing | C36: Junior Marketing Coordinator | D36: Remote | E36: Firm-wide | I36: =IF(G36="","",G36/(160*H36)-1) | J36: Social Media; Content Writing; Canva | K36: Available | L36: 46174 | M36: New marketing support role
A37: TBD | B37: Operations | C37: Junior IT Support | D37: New York | E37: IT Infrastructure | I37: =IF(G37="","",G37/(160*H37)-1) | J37: IT Support; Help Desk; Network Admin | K37: Available | L37: 46204 | M37: Growing IT needs
A39: SUMMARY
A40: Total Billable Hours | B40: =SUM(G2:G37) -> 2101
A41: Average Allocation | B41: =AVERAGE(F2:F37) -> 0.67954545
A42: Overallocated Staff Count | B42: =COUNTIF(F2:F37,">1") -> 1

Sheet Project Portfolio
A1: Project Name | B1: Typology | C1: Location | D1: Phase | E1: Contract Fee | F1: Fee Method | G1: Reimbursable Pct | H1: Square Footage | I1: Construction Cost Estimate | J1: Hours Planned | K1: Hours Actual | L1: Hours Remaining | M1: Hours Variance | N1: Staff Assigned | O1: Consultant Costs | P1: Change Orders | Q1: Start Date | R1: Target Completion
A2: Shore Club Residences | B2: Residential Condo | C2: Fort Lauderdale FL | D2: CD | E2: 4200000 | F2: Percentage | G2: 0.12 | H2: 385000 | I2: 78000000 | J2: 28000 | K2: 31200 | L2: =J2-K2 -> -3200 | M2: =K2/J2-1 -> 0.11428571 | N2: 8 | O2: 1450000 | P2: 3 | Q2: 45337 | R2: 46235
A3: Riverside Tower | B3: Residential Rental | C3: New York NY | D3: DD | E3: 3100000 | F3: Time & Resources | G3: 0.1 | H3: 265000 | I3: 52000000 | J3: 22000 | K3: 18500 | L3: =J3-K3 -> 3500 | M3: =K3/J3-1 -> -0.15909091 | N3: 6 | O3: 980000 | P3: 1 | Q3: 45444 | R3: 46341
A4: Harbor View Residences | B4: Residential Condo | C4: Jersey City NJ | D4: CA | E4: 2800000 | F4: Percentage | G4: 0.15 | H4: 210000 | I4: 44000000 | J4: 19000 | K4: 20100 | L4: =J4-K4 -> -1100 | M4: =K4/J4-1 -> 0.057894737 | N4: 5 | O4: 870000 | P4: 4 | Q4: 44936 | R4: 46021
A5: Wynwood Arts Mixed-Use | B5: Mixed-Use | C5: Miami FL | D5: CA | E5: 3500000 | F5: Fixed Fee | G5: 0.1 | H5: 295000 | I5: 61000000 | J5: 24000 | K5: 23800 | L5: =J5-K5 -> 200 | M5: =K5/J5-1 -> -0.0083333333 | N5: 7 | O5: 1120000 | P5: 2 | Q5: 45005 | R5: 45915
A6: Jersey City Waterfront Tower | B6: Residential Condo | C6: Jersey City NJ | D6: SD | E6: 2400000 | F6: Percentage | G6: 0.12 | H6: 225000 | I6: 47000000 | J6: 16000 | K6: 4200 | L6: =J6-K6 -> 11800 | M6: =K6/J6-1 -> -0.7375 | N6: 4 | O6: 340000 | P6: 0 | Q6: 45901 | R6: 46813
A7: Hoboken Residential | B7: Residential Rental | C7: Hoboken NJ | D7: DD | E7: 1800000 | F7: Time & Resources | G7: 0.1 | H7: 142000 | I7: 29500000 | J7: 14000 | K7: 9800 | L7: =J7-K7 -> 4200 | M7: =K7/J7-1 -> -0.3 | N7: 4 | O7: 520000 | P7: 1 | Q7: 45597 | R7: 46402
A8: The Mira Hotel & Residences | B8: Hospitality | C8: Dubai UAE | D8: SD | E8: 5600000 | F8: Percentage | G8: 0.15 | H8: 410000 | I8: 125000000 | J8: 35000 | K8: 8900 | L8: =J8-K8 -> 26100 | M8: =K8/J8-1 -> -0.74571429 | N8: 6 | O8: 680000 | P8: 0 | Q8: 45823 | R8: 47119
A9: Upstate Condo | B9: Residential Condo | C9: Hudson Valley NY | D9: DD | E9: 1950000 | F9: Fixed Fee | G9: 0.1 | H9: 168000 | I9: 34000000 | J9: 15000 | K9: 11200 | L9: =J9-K9 -> 3800 | M9: =K9/J9-1 -> -0.25333333 | N9: 5 | O9: 610000 | P9: 2 | Q9: 45505 | R9: 46478
A10: Fort Lauderdale Cultural Center | B10: Cultural | C10: Fort Lauderdale FL | D10: CA | E10: 2200000 | F10: Percentage | G10: 0.12 | H10: 88000 | I10: 22000000 | J10: 17000 | K10: 17600 | L10: =J10-K10 -> -600 | M10: =K10/J10-1 -> 0.035294118 | N10: 4 | O10: 540000 | P10: 1 | Q10: 44805 | R10: 45838
A11: Mayflower | B11: Residential Condo | C11: New York NY | D11: CD | E11: 3800000 | F11: Time & Resources | G11: 0.12 | H11: 310000 | I11: 64000000 | J11: 26000 | K11: 24100 | L11: =J11-K11 -> 1900 | M11: =K11/J11-1 -> -0.073076923 | N11: 7 | O11: 1280000 | P11: 2 | Q11: 45245 | R11: 46143
A12: TOTALS | E12: =SUM(E2:E11) -> 31350000 | H12: =SUM(H2:H11) -> 2498000 | I12: =SUM(I2:I11) -> 556500000 | J12: =SUM(J2:J11) -> 216000 | K12: =SUM(K2:K11) -> 169400 | N12: =SUM(N2:N11) -> 56 | O12: =SUM(O2:O11) -> 8390000 | P12: =SUM(P2:P11) -> 16

Sheet Financial Summary
A1: Metric | B1: Value | C1: Notes
A2: Total Revenue (15 months) | B2: =SUM('Monthly Financials'!B2:B16) -> 7505000 | C2: Sum of all monthly revenue
A3: Total Expenses (15 months) | B3: =SUM('Monthly Financials'!C2:C16) -> 6225000 | C3: Sum of all monthly expenses
A4: Total Net Profit (15 months) | B4: =SUM('Monthly Financials'!D2:D16) -> 1280000 | C4: Revenue minus expenses over period
A5: Average Monthly Revenue | B5: =AVERAGE('Monthly Financials'!B2:B16) -> 500333.33 | C5: Mean monthly revenue
A6: Average Monthly Expenses | B6: =AVERAGE('Monthly Financials'!C2:C16) -> 415000 | C6: Mean monthly expenses
A7: Average Profit Margin | B7: =AVERAGE('Monthly Financials'!E2:E16) -> 0.16600747 | C7: Mean profit margin percentage
A8: Highest Revenue Month | B8: =MAX('Monthly Financials'!B2:B16) -> 595000 | C8: Peak monthly revenue
A9: Lowest Revenue Month | B9: =MIN('Monthly Financials'!B2:B16) -> 415000 | C9: Lowest monthly revenue
A10: Revenue Volatility | B10: =_xlfn.STDEV.P('Monthly Financials'!B2:B16) -> 53773.186 | C10: Standard deviation of revenue
A11: Total Active Projects (Latest) | B11: ='Monthly Financials'!F16 -> 14 | C11: Projects active in Mar 2026
A12: Total Commissions (15 months) | B12: =SUM('Monthly Financials'!G2:G16) -> 27 | C12: Total new projects won
A13: Current Staff Count | B13: ='Monthly Financials'!H16 -> 28 | C13: Staff headcount as of Mar 2026
A14: Average Utilization Rate | B14: =AVERAGE('Monthly Financials'!I2:I16) -> 0.76466667 | C14: Mean staff utilization percentage

Sheet Project Dashboard
A1: Metric | B1: Value | C1: Notes | E1: Phase | F1: Count
A2: Total Portfolio Value | B2: =SUM('Project Portfolio'!E2:E11) -> 31350000 | C2: Sum of all contract fees | E2: SD | F2: =COUNTIF('Project Portfolio'!D2:D11,"SD") -> 2
A3: Average Contract Fee | B3: =AVERAGE('Project Portfolio'!E2:E11) -> 3135000 | C3: Mean project fee | E3: DD | F3: =COUNTIF('Project Portfolio'!D2:D11,"DD") -> 3
A4: Largest Project Fee | B4: =MAX('Project Portfolio'!E2:E11) -> 5600000 | C4: Highest contract value | E4: CD | F4: =COUNTIF('Project Portfolio'!D2:D11,"CD") -> 2
A5: Total Construction Cost | B5: =SUM('Project Portfolio'!I2:I11) -> 556500000 | C5: Sum of estimated construction costs | E5: CA | F5: =COUNTIF('Project Portfolio'!D2:D11,"CA") -> 3
A6: Total Square Footage | B6: =SUM('Project Portfolio'!H2:H11) -> 2498000 | C6: Total building area across portfolio
A7: Average SF per Project | B7: =AVERAGE('Project Portfolio'!H2:H11) -> 249800 | C7: Mean project size
A8: Total Hours Planned | B8: =SUM('Project Portfolio'!J2:J11) -> 216000 | C8: Budgeted hours across all projects
A9: Total Hours Actual | B9: =SUM('Project Portfolio'!K2:K11) -> 169400 | C9: Hours spent to date
A10: Overall Hours Variance | B10: =SUM('Project Portfolio'!K2:K11)/SUM('Project Portfolio'!J2:J11)-1 -> -0.21574074 | C10: Portfolio-level hours performance
A11: Total Staff Assigned | B11: =SUM('Project Portfolio'!N2:N11) -> 56 | C11: Staff allocated to projects
A12: Total Consultant Costs | B12: =SUM('Project Portfolio'!O2:O11) -> 8390000 | C12: External consultant expenses
A13: Total Change Orders | B13: =SUM('Project Portfolio'!P2:P11) -> 16 | C13: Change orders issued
A14: Projects in SD | B14: =COUNTIF('Project Portfolio'!D2:D11,"SD") -> 2 | C14: Schematic Design phase
A15: Projects in DD | B15: =COUNTIF('Project Portfolio'!D2:D11,"DD") -> 3 | C15: Design Development phase
A16: Projects in CD | B16: =COUNTIF('Project Portfolio'!D2:D11,"CD") -> 2 | C16: Construction Documents phase
A17: Projects in CA | B17: =COUNTIF('Project Portfolio'!D2:D11,"CA") -> 3 | C17: Construction Administration phase
A18: Projects Over Budget (hours) | B18: =COUNTIF('Project Portfolio'!M2:M11,">0") -> 3 | C18: Projects exceeding planned hours

Sheet Sources
A1: Title | B1: URL
A2: oda-monthly-financials.csv | B2: https://advai-my.sharepoint.com/personal/noam_advas_ai/_layouts/15/Doc.aspx?sourcedoc=%7B0387F033-9C6E-487E-B82C-A8E3E11CBE36%7D&file=oda-monthly-financials.csv&action=default&mobileredirect=true
A3: ODA-Resource-Allocation.xlsx | B3: https://advai-my.sharepoint.com/personal/noam_advas_ai/_layouts/15/Doc.aspx?sourcedoc=%7B9797469E-5A40-480A-8ECC-138FF42CFE28%7D&file=ODA-Resource-Allocation.xlsx&action=default&mobileredirect=true&DefaultItemOpen=1
A4: oda-project-tracking.csv | B4: https://advai-my.sharepoint.com/personal/noam_advas_ai/_layouts/15/Doc.aspx?sourcedoc=%7B9105F584-62EA-43BE-AA7D-8315CACC7160%7D&file=oda-project-tracking.csv&action=default&mobileredirect=true
